{
  "accel_to_decel_enable": "0",
  "bridge_angle": "45",
  "brim_type": "no_brim",
  "brim_width": "5",
  "detect_thin_wall": "0",
  "enable_prime_tower": "1",
  "filename_format": "{input_filename_base}_{filament_type[0]}_{print_time}.gcode",
  "filter_out_gap_fill": "0",
  "from": "User",
  "fuzzy_skin_point_distance": "0.8",
  "fuzzy_skin_thickness": "0.3",
  "gap_infill_speed": "200",
  "gcode_label_objects": "1",
  "independent_support_layer_height": "1",
  "inherits": "0.28mm Extra Draft @Creality Ender-3 V3",
  "initial_layer_infill_speed": "150",
  "initial_layer_line_width": "0.75",
  "initial_layer_speed": "80",
  "initial_layer_travel_speed": "100%",
  "inner_wall_acceleration": "0",
  "inner_wall_line_width": "0.75",
  "inner_wall_speed": "150",
  "internal_solid_infill_line_width": "0.45",
  "internal_solid_infill_pattern": "rectilinear",
  "internal_solid_infill_speed": "250",
  "ironing_angle": "45",
  "ironing_flow": "10%",
  "ironing_inset": "0.21",
  "ironing_spacing": "0.15",
  "is_custom_defined": "0",
  "layer_height": "0.25",
  "line_width": "0.75",
  "max_bridge_length": "0",
  "name": "ModuBOX-Ender-3-Boxes",
  "notes": "",
  "outer_wall_acceleration": "5000",
  "outer_wall_line_width": "0.65",
  "outer_wall_speed": "100",
  "overhang_1_4_speed": "100%",
  "overhang_2_4_speed": "75%",
  "overhang_3_4_speed": "55%",
  "overhang_4_4_speed": "35%",
  "precise_outer_wall": "0",
  "prime_tower_width": "35",
  "print_settings_id": "ModuBOX-Ender-3-Boxes",
  "raft_first_layer_expansion": "1",
  "seam_slope_conditional": "1",
  "seam_slope_inner_walls": "1",
  "seam_slope_min_length": "10",
  "seam_slope_start_height": "10%",
  "skeleton_infill_density": "5%",
  "skeleton_infill_line_width": "0.45",
  "skin_infill_density": "5%",
  "skin_infill_line_width": "0.45",
  "skirt_loops": "0",
  "small_perimeter_threshold": "0",
  "sparse_infill_density": "5%",
  "sparse_infill_line_width": "0.75",
  "sparse_infill_pattern": "grid",
  "sparse_infill_speed": "160",
  "support_base_pattern": "default",
  "support_interface_bottom_layers": "2",
  "support_interface_top_layers": "2",
  "support_style": "default",
  "support_threshold_angle": "40",
  "support_top_z_distance": "0.2",
  "support_type": "tree(auto)",
  "top_surface_speed": "250",
  "travel_jerk": "9",
  "tree_support_branch_angle": "45",
  "tree_support_wall_count": "-1",
  "version": "0.0.0.0",
  "wall_generator": "arachne"
}
